pycololighto/__init__.py
pycololighto/constants.py
pycololighto/effects.py
pycololighto/pycololight.py
pycololighto-2.1.1.dist-info/LICENSE
pycololighto-2.1.1.dist-info/METADATA
pycololighto-2.1.1.dist-info/WHEEL
pycololighto-2.1.1.dist-info/RECORD
