Metadata-Version: 2.3
Name: pycololighto
Version: 2.1.1
Summary: A Python3 wrapper for interacting with LifeSmart Cololight, forked from BazaJayGee66 with some tweaks
License: MIT
Author: BazaJayGee66
Requires-Python: >=3.8,<4.0
Classifier: License :: OSI Approved :: MIT License
Classifier: Programming Language :: Python :: 3
Classifier: Programming Language :: Python :: 3.8
Classifier: Programming Language :: Python :: 3.9
Classifier: Programming Language :: Python :: 3.10
Classifier: Programming Language :: Python :: 3.11
Classifier: Programming Language :: Python :: 3.12
Classifier: Programming Language :: Python :: 3.13
Project-URL: Repository, https://github.com/leoyesaulov/pycololight
